{
    "credit": "Made with Blockbench",
    "parent": "./cit_item_ceilingflower",
    "textures": {
        "leaves_0": "./oak_leaves_0",
        "leaves_1": "./oak_leaves_1"
    },
    "elements": [
        {
            "from": [
                -1,
                0,
                8
            ],
            "to": [
                17,
                32,
                8.01
            ],
            "rotation": {
                "angle": 45,
                "axis": "y",
                "origin": [
                    8,
                    12,
                    8
                ]
            },
            "faces": {
                "north": {
                    "uv": [
                        0,
                        0,
                        8,
                        16
                    ],
                    "texture": "#0"
                },
                "south": {
                    "uv": [
                        0,
                        0,
                        8,
                        16
                    ],
                    "texture": "#0"
                }
            }
        },
        {
            "from": [
                -1,
                0,
                6
            ],
            "to": [
                17,
                32,
                10
            ],
            "rotation": {
                "angle": 45,
                "axis": "y",
                "origin": [
                    8,
                    12,
                    8
                ]
            },
            "faces": {
                "north": {
                    "uv": [
                        8,
                        0,
                        16,
                        16
                    ],
                    "texture": "#0"
                },
                "south": {
                    "uv": [
                        8,
                        0,
                        16,
                        16
                    ],
                    "texture": "#0"
                }
            }
        },
        {
            "from": [
                7.99,
                0,
                -1
            ],
            "to": [
                8,
                32,
                17
            ],
            "rotation": {
                "angle": 45,
                "axis": "y",
                "origin": [
                    8,
                    12,
                    8
                ]
            },
            "faces": {
                "east": {
                    "uv": [
                        0,
                        0,
                        8,
                        16
                    ],
                    "texture": "#0"
                },
                "west": {
                    "uv": [
                        0,
                        0,
                        8,
                        16
                    ],
                    "texture": "#0"
                }
            }
        },
        {
            "from": [
                6,
                0,
                -1
            ],
            "to": [
                10,
                32,
                17
            ],
            "rotation": {
                "angle": 45,
                "axis": "y",
                "origin": [
                    8,
                    12,
                    8
                ]
            },
            "faces": {
                "east": {
                    "uv": [
                        8,
                        0,
                        16,
                        16
                    ],
                    "texture": "#0"
                },
                "west": {
                    "uv": [
                        8,
                        0,
                        16,
                        16
                    ],
                    "texture": "#0"
                }
            }
        },
        {
            "from": [
                7.99,
                -16,
                -1
            ],
            "to": [
                8,
                16,
                17
            ],
            "rotation": {
                "angle": 45,
                "axis": "y",
                "origin": [
                    8,
                    12,
                    8
                ]
            },
            "faces": {
                "east": {
                    "uv": [
                        0,
                        0,
                        8,
                        16
                    ],
                    "texture": "#1"
                },
                "west": {
                    "uv": [
                        0,
                        0,
                        8,
                        16
                    ],
                    "texture": "#1"
                }
            }
        },
        {
            "from": [
                6,
                -16,
                -1
            ],
            "to": [
                10,
                16,
                17
            ],
            "rotation": {
                "angle": 45,
                "axis": "y",
                "origin": [
                    8,
                    12,
                    8
                ]
            },
            "faces": {
                "east": {
                    "uv": [
                        8,
                        0,
                        16,
                        16
                    ],
                    "texture": "#1"
                },
                "west": {
                    "uv": [
                        8,
                        0,
                        16,
                        16
                    ],
                    "texture": "#1"
                }
            }
        },
        {
            "from": [
                -1,
                -16,
                8
            ],
            "to": [
                17,
                16,
                8.01
            ],
            "rotation": {
                "angle": 45,
                "axis": "y",
                "origin": [
                    8,
                    12,
                    8
                ]
            },
            "faces": {
                "north": {
                    "uv": [
                        0,
                        0,
                        8,
                        16
                    ],
                    "texture": "#1"
                },
                "south": {
                    "uv": [
                        0,
                        0,
                        8,
                        16
                    ],
                    "texture": "#1"
                }
            }
        },
        {
            "from": [
                -1,
                -16,
                6
            ],
            "to": [
                17,
                16,
                10
            ],
            "rotation": {
                "angle": 45,
                "axis": "y",
                "origin": [
                    8,
                    12,
                    8
                ]
            },
            "faces": {
                "north": {
                    "uv": [
                        8,
                        0,
                        16,
                        16
                    ],
                    "texture": "#1"
                },
                "south": {
                    "uv": [
                        8,
                        0,
                        16,
                        16
                    ],
                    "texture": "#1"
                }
            }
        }
    ]
}