{
	"parent": "./cit_item",
	"textures": {
		"0": "./lifebuoy"
	},
	"elements": [
		{
			"from": [3, 0, 1],
			"to": [13, 3, 5],
			"faces": {
				"north": {"uv": [6, 4, 16, 7], "texture": "#0"},
				"east": {"uv": [8, 7, 12, 10], "texture": "#0"},
				"south": {"uv": [16, 4, 6, 7], "texture": "#0"},
				"west": {"uv": [12, 7, 16, 10], "texture": "#0"},
				"up": {"uv": [2, 0, 12, 4], "texture": "#0"},
				"down": {"uv": [2, 4, 12, 0], "texture": "#0"}
			}
		},
		{
			"from": [3, 0, 11],
			"to": [13, 3, 15],
			"faces": {
				"north": {"uv": [16, 4, 6, 7], "texture": "#0"},
				"east": {"uv": [12, 7, 16, 10], "texture": "#0"},
				"south": {"uv": [6, 4, 16, 7], "texture": "#0"},
				"west": {"uv": [8, 7, 12, 10], "texture": "#0"},
				"up": {"uv": [12, 4, 2, 0], "texture": "#0"},
				"down": {"uv": [12, 0, 2, 4], "texture": "#0"}
			}
		},
		{
			"from": [1, 0, 3],
			"to": [5, 3, 13],
			"faces": {
				"north": {"uv": [12, 7, 16, 10], "texture": "#0"},
				"east": {"uv": [6, 4, 16, 7], "texture": "#0"},
				"south": {"uv": [8, 7, 12, 10], "texture": "#0"},
				"west": {"uv": [16, 4, 6, 7], "texture": "#0"},
				"up": {"uv": [0, 2, 4, 12], "texture": "#0"},
				"down": {"uv": [0, 12, 4, 2], "texture": "#0"}
			}
		},
		{
			"from": [11, 0, 3],
			"to": [15, 3, 13],
			"faces": {
				"north": {"uv": [8, 7, 12, 10], "texture": "#0"},
				"east": {"uv": [16, 4, 6, 7], "texture": "#0"},
				"south": {"uv": [12, 7, 16, 10], "texture": "#0"},
				"west": {"uv": [6, 4, 16, 7], "texture": "#0"},
				"up": {"uv": [4, 12, 0, 2], "texture": "#0"},
				"down": {"uv": [4, 2, 0, 12], "texture": "#0"}
			}
		},
		{
			"from": [7.5, -0.5, 0.5],
			"to": [8.5, 3.5, 5.5],
			"faces": {
				"north": {"uv": [11, 12, 12, 16], "texture": "#0"},
				"east": {"uv": [11, 12, 16, 16], "texture": "#0"},
				"south": {"uv": [15, 12, 16, 16], "texture": "#0"},
				"west": {"uv": [11, 12, 16, 16], "texture": "#0"},
				"up": {"uv": [10, 11, 11, 16], "texture": "#0"},
				"down": {"uv": [10, 11, 11, 16], "texture": "#0"}
			}
		}
	]
}